[  
  { "country_name": "Algeria", "iso_code": "DZ", "currency": "Algerian Dinar", "currency_code": "DZD", "exchange_rate_placeholder": null },
  { "country_name": "Angola", "iso_code": "AO", "currency": "Angolan Kwanza", "currency_code": "AOA", "exchange_rate_placeholder": null },
  { "country_name": "Benin", "iso_code": "BJ", "currency": "CFA Franc", "currency_code": "XOF", "exchange_rate_placeholder": null },
  { "country_name": "Botswana", "iso_code": "BW", "currency": "Botswana Pula", "currency_code": "BWP", "exchange_rate_placeholder": null },
  { "country_name": "Burkina Faso", "iso_code": "BF", "currency": "CFA Franc", "currency_code": "XOF", "exchange_rate_placeholder": null },
  { "country_name": "Burundi", "iso_code": "BI", "currency": "Burundian Franc", "currency_code": "BIF", "exchange_rate_placeholder": null },
  { "country_name": "Cabo Verde", "iso_code": "CV", "currency": "Cabo Verdean Escudo", "currency_code": "CVE", "exchange_rate_placeholder": null },
  { "country_name": "Cameroon", "iso_code": "CM", "currency": "CFA Franc", "currency_code": "XOF", "exchange_rate_placeholder": null },
  { "country_name": "Central African Republic", "iso_code": "CF", "currency": "Central African CFA Franc", "currency_code": "XAF", "exchange_rate_placeholder": null },
  { "country_name": "Chad", "iso_code": "TD", "currency": "Central African CFA Franc", "currency_code": "XAF", "exchange_rate_placeholder": null },
  { "country_name": "Comoros", "iso_code": "KM", "currency": "Comorian Franc", "currency_code": "KMF", "exchange_rate_placeholder": null },
  { "country_name": "Congo, Democratic Republic of the", "iso_code": "CD", "currency": "Congolese Franc", "currency_code": "CDF", "exchange_rate_placeholder": null },
  { "country_name": "Congo, Republic of the", "iso_code": "CG", "currency": "Central African CFA Franc", "currency_code": "XAF", "exchange_rate_placeholder": null },
  { "country_name": "Djibouti", "iso_code": "DJ", "currency": "Djiboutian Franc", "currency_code": "DJF", "exchange_rate_placeholder": null },
  { "country_name": "Egypt", "iso_code": "EG", "currency": "Egyptian Pound", "currency_code": "EGP", "exchange_rate_placeholder": null },
  { "country_name": "Equatorial Guinea", "iso_code": "GQ", "currency": "Central African CFA Franc", "currency_code": "XAF", "exchange_rate_placeholder": null },
  { "country_name": "Eswatini", "iso_code": "SZ", "currency": "Swazi Lilangeni", "currency_code": "SZL", "exchange_rate_placeholder": null },
  { "country_name": "Ethiopia", "iso_code": "ET", "currency": "Ethiopian Birr", "currency_code": "ETB", "exchange_rate_placeholder": null },
  { "country_name": "Gabon", "iso_code": "GA", "currency": "Central African CFA Franc", "currency_code": "XAF", "exchange_rate_placeholder": null },
  { "country_name": "Gambia", "iso_code": "GM", "currency": "Gambian Dalasi", "currency_code": "GMD", "exchange_rate_placeholder": null },
  { "country_name": "Ghana", "iso_code": "GH", "currency": "Ghanaian Cedi", "currency_code": "GHS", "exchange_rate_placeholder": null },
  { "country_name": "Guinea", "iso_code": "GN", "currency": "Guinean Franc", "currency_code": "GNF", "exchange_rate_placeholder": null },
  { "country_name": "Guinea-Bissau", "iso_code": "GW", "currency": "CFA Franc", "currency_code": "XOF", "exchange_rate_placeholder": null },
  { "country_name": "Ivory Coast", "iso_code": "CI", "currency": "CFA Franc", "currency_code": "XOF", "exchange_rate_placeholder": null },
  { "country_name": "Kenya", "iso_code": "KE", "currency": "Kenyan Shilling", "currency_code": "KES", "exchange_rate_placeholder": null },
  { "country_name": "Lesotho", "iso_code": "LS", "currency": "Lesotho Loti", "currency_code": "LSL", "exchange_rate_placeholder": null },
  { "country_name": "Liberia", "iso_code": "LR", "currency": "Liberian Dollar", "currency_code": "LRD", "exchange_rate_placeholder": null },
  { "country_name": "Libya", "iso_code": "LY", "currency": "Libyan Dinar", "currency_code": "LYD", "exchange_rate_placeholder": null },
  { "country_name": "Madagascar", "iso_code": "MG", "currency": "Malagasy Ariary", "currency_code": "MGA", "exchange_rate_placeholder": null },
  { "country_name": "Malawi", "iso_code": "MW", "currency": "Malawian Kwacha", "currency_code": "MWK", "exchange_rate_placeholder": null },
  { "country_name": "Mali", "iso_code": "ML", "currency": "CFA Franc", "currency_code": "XOF", "exchange_rate_placeholder": null },
  { "country_name": "Mauritania", "iso_code": "MR", "currency": "Ouguiya", "currency_code": "MRU", "exchange_rate_placeholder": null },
  { "country_name": "Mauritius", "iso_code": "MU", "currency": "Mauritian Rupee", "currency_code": "MUR", "exchange_rate_placeholder": null },
  { "country_name": "Morocco", "iso_code": "MA", "currency": "Moroccan Dirham", "currency_code": "MAD", "exchange_rate_placeholder": null },
  { "country_name": "Mozambique", "iso_code": "MZ", "currency": "Mozambican Metical", "currency_code": "MZN", "exchange_rate_placeholder": null },
  { "country_name": "Namibia", "iso_code": "NA", "currency": "Namibian Dollar", "currency_code": "NAD", "exchange_rate_placeholder": null },
  { "country_name": "Niger", "iso_code": "NE", "currency": "Nigerien Franc", "currency_code": "XOF", "exchange_rate_placeholder": null },
  { "country_name": "Nigeria", "iso_code": "NG", "currency": "Nigerian Naira", "currency_code": "NGN", "exchange_rate_placeholder": null },
  { "country_name": "Rwanda", "iso_code": "RW", "currency": "Rwandan Franc", "currency_code": "RWF", "exchange_rate_placeholder": null },
  { "country_name": "Sao Tome and Principe", "iso_code": "ST", "currency": "Dobra", "currency_code": "STN", "exchange_rate_placeholder": null },
  { "country_name": "Senegal", "iso_code": "SN", "currency": "CFA Franc", "currency_code": "XOF", "exchange_rate_placeholder": null },
  { "country_name": "Seychelles", "iso_code": "SC", "currency": "Seychellois Rupee", "currency_code": "SCR", "exchange_rate_placeholder": null },
  { "country_name": "Sierra Leone", "iso_code": "SL", "currency": "Sierra Leonean Leone", "currency_code": "SLL", "exchange_rate_placeholder": null },
  { "country_name": "Somalia", "iso_code": "SO", "currency": "Somali Shilling", "currency_code": "SOS", "exchange_rate_placeholder": null },
  { "country_name": "South Africa", "iso_code": "ZA", "currency": "South African Rand", "currency_code": "ZAR", "exchange_rate_placeholder": null },
  { "country_name": "South Sudan", "iso_code": "SS", "currency": "South Sudanese Pound", "currency_code": "SSP", "exchange_rate_placeholder": null },
  { "country_name": "Sudan", "iso_code": "SD", "currency": "Sudanese Pound", "currency_code": "SDG", "exchange_rate_placeholder": null },
  { "country_name": "Tanzania", "iso_code": "TZ", "currency": "Tanzanian Shilling", "currency_code": "TZS", "exchange_rate_placeholder": null },
  { "country_name": "Togo", "iso_code": "TG", "currency": "CFA Franc", "currency_code": "XOF", "exchange_rate_placeholder": null },
  { "country_name": "Tunisia", "iso_code": "TN", "currency": "Tunisian Dinar", "currency_code": "TND", "exchange_rate_placeholder": null },
  { "country_name": "Uganda", "iso_code": "UG", "currency": "Ugandan Shilling", "currency_code": "UGX", "exchange_rate_placeholder": null },
  { "country_name": "Zambia", "iso_code": "ZM", "currency": "Zambian Kwacha", "currency_code": "ZMW", "exchange_rate_placeholder": null },
  { "country_name": "Zimbabwe", "iso_code": "ZW", "currency": "Zimbabwean Dollar", "currency_code": "ZWL", "exchange_rate_placeholder": null }
]